[
    {
        "name": "Game",
        "description": "",
        "logo": "game.png",
        "url": "https://gamenet.one/",
        "address": "https://gamenet.one",
        "status": "inactive",
        "uptime": "0",
        "commision": "5",
        "apr": null,
        "price": "",
        "staked_user": "",
        "staked_amount": ""
    },
    {
        "name": "Anone",
        "description": "",
        "logo": "anone.jpg",
        "url": "https://another-1.io/",
        "address": "https://test-anone.zenscan.io/validator.php?addr=onevaloper1yxafnfes6ax62n9snjs44aweyxalsz0hgvjfr0",
        "status": "inactive",
        "uptime": "0",
        "commision": "5",
        "apr": null,
        "price": "",
        "staked_user": "",
        "staked_amount": ""
    },
    {
        "name": "Crescent",
        "description": "",
        "logo": "cresent.jpeg",
        "url": "https://crescent.network/",
        "address": "https://testnet.explorer.crescent.nodes.guru/validator/crevaloper12rxjrwu4wcglzgulmp8gq5vfskjtyadyztludk",
        "status": "inactive",
        "uptime": "0",
        "commision": "5",
        "apr": null,
        "price": "",
        "staked_user": "",
        "staked_amount": ""
    },
    {
        "name": "Cosmic Horizon",
        "description": "",
        "logo": "cosmic.jpeg",
        "url": "https://cosmic-horizon.com/",
        "address": "https://cosmic-horizon.com/",
        "status": "inactive",
        "uptime": "0",
        "commision": "5",
        "apr": {
            "inflation": "https://coho-test.postcapitalist.io/minting/inflation",
            "communityTax": "https://coho-test.postcapitalist.io/distribution/parameters",
            "supply": "https://coho-test.postcapitalist.io/cosmos/bank/v1beta1/supply/ucoho",
            "pool": "https://coho-test.postcapitalist.io/staking/pool",
            "blocktime": "6"
        },
        "price": "",
        "staked_user": "",
        "staked_amount": ""
    },
    {
        "name": "Galaxy",
        "description": "",
        "logo": "galaxy.jpeg",
        "url": "https://galaxychain.zone/",
        "address": "https://testnet.postcapitalist.io/Galaxy/staking/galaxyvaloper16uv9d64qawhgrjfst46tce4k52d5ur45cmg8gh",
        "status": "inactive",
        "uptime": "0",
        "commision": "10",
        "apr": null,
        "price": "",
        "staked_user": "",
        "staked_amount": ""
    },
    {
        "name": "Sei Network",
        "description": "",
        "logo": "sei.jpeg",
        "url": "https://www.seinetwork.io/",
        "address": "https://sei.explorers.guru/validator/seivaloper1z4g50l9uxll3ypua8pd9gesf7jay8l9s5nehgj",
        "status": "inactive",
        "uptime": "0",
        "commision": "10",
        "apr": null,
        "price": "",
        "staked_user": "",
        "staked_amount": ""
    },
    {
        "name": "Teritori",
        "description": "",
        "logo": "teritori.jpg",
        "url": "https://teritori.com/",
        "address": "",
        "status": "inactive",
        "uptime": "0",
        "commision": "5",
        "apr": null,
        "price": "",
        "staked_user": "",
        "staked_amount": ""
    },
    {
        "name": "Quicksilver",
        "description": "",
        "logo": "quicksilver.jpeg",
        "url": "https://quicksilver.zone/",
        "address": "https://quicksilver.explorers.guru/validator/quickvaloper1t0ucq9tvtged36hgzdwsu84g2ly0m9tacwe9ca",
        "status": "inactive",
        "uptime": "0",
        "commision": "5.9",
        "apr": null,
        "price": "",
        "staked_user": "",
        "staked_amount": ""
    },
    {
        "name": "OKP4",
        "description": "OKP4 is a domain-specific layer-1 dedicated to trust-minimized data sharing.",
        "logo": "okp4.png",
        "url": "https://okp4.network/",
        "address": "",
        "status": "inactive",
        "uptime": "100",
        "commision": "5",
        "apr": null,
        "price": "",
        "staked_user": "",
        "staked_amount": ""
    },
    {
        "name": "Aura Network",
        "description": "",
        "logo": "aura.png",
        "url": "https://aura.network/",
        "address": "https://testnet.explorer.tcnetwork.io/aura/validator/auravaloper1x974kw0xsasgr574h9vpaggg8dhn7yxgjmawye",
        "status": "active",
        "uptime": "100",
        "commision": "5",
        "apr": null,
        "price": "",
        "staked_user": "",
        "staked_amount": ""
    },
    {
        "name": "Gitopia",
        "description": "",
        "logo": "gitopia.png",
        "url": "https://gitopia.com/",
        "address": "https://testnet.explorer.tcnetwork.io/gitopia/validator/gitopiavaloper1xr5980r6e7cy3u3pfm5xq2ruh5d3xy6ah6w98y",
        "status": "active",
        "uptime": "100",
        "commision": "5",
        "apr": null,
        "price": "",
        "staked_user": "",
        "staked_amount": ""
    },
    {
        "name": "Hypersign",
        "description": "",
        "logo": "hypersign.jpg",
        "url": "https://hypersign.id/",
        "address": "https://testnet.explorer.tcnetwork.io/hypersign/validator/hidvaloper16re2zprhnekq62qmcuh7v0dxtsa7le3nmyq8zs",
        "status": "active",
        "uptime": "100",
        "commision": "5",
        "apr": null,
        "price": "",
        "staked_user": "",
        "staked_amount": ""
    },
    {
        "name": "Defund",
        "description": "",
        "logo": "defund.png",
        "url": "https://www.defund.app/",
        "address": "https://testnet.explorer.tcnetwork.io/defund/validator/defundvaloper1hv6v4evs5udxxq9cx8jn5fskjtxx20ha83pyc2",
        "status": "active",
        "uptime": "100",
        "commision": "10",
        "apr": null,
        "price": "",
        "staked_user": "",
        "staked_amount": ""
    },
    {
        "name": "MUN",
        "description": "",
        "logo": "mun.jpg",
        "url": "https://mun.money/",
        "address": "https://testnet.explorer.tcnetwork.io/mun/validator/munvaloper1pzfy45z6ysd9c0fp83fczt6zhusulr45z8xflq",
        "status": "active",
        "uptime": "100",
        "commision": "5",
        "apr": null,
        "price": "",
        "staked_user": "",
        "staked_amount": ""
    },
    {
        "name": "Ollo Station",
        "description": "",
        "logo": "ollo.svg",
        "url": "https://www.ollostation.zone/",
        "address": "https://testnet.explorer.tcnetwork.io/ollo/validator/ollovaloper1pzfy45z6ysd9c0fp83fczt6zhusulr4557mnep",
        "status": "active",
        "uptime": "100",
        "commision": "5",
        "apr": null,
        "price": "",
        "staked_user": "",
        "staked_amount": ""
    },
    {
        "name": "Nibitu",
        "description": "",
        "logo": "nibiru.png",
        "url": "https://nibiru.fi/",
        "address": "https://testnet.explorer.tcnetwork.io/nibiru/validator/nibivaloper16re2zprhnekq62qmcuh7v0dxtsa7le3nctm7zy",
        "status": "active",
        "uptime": "100",
        "commision": "5",
        "apr": null,
        "price": "",
        "staked_user": "",
        "staked_amount": ""
    },
    {
        "name": "Nolus",
        "description": "",
        "logo": "nolus.png",
        "url": "https://nolus.io/",
        "address": "https://testnet.explorer.tcnetwork.io/nolus/validator/nolusvaloper16re2zprhnekq62qmcuh7v0dxtsa7le3nf45x7j",
        "status": "active",
        "uptime": "100",
        "commision": "5",
        "apr": null,
        "price": "",
        "staked_user": "",
        "staked_amount": ""
    },
    {
        "name": "Lava",
        "description": "",
        "logo": "lava.png",
        "url": "https://lavanet.xyz/",
        "address": "https://testnet.explorer.tcnetwork.io/lava/validator/lava@valoper16re2zprhnekq62qmcuh7v0dxtsa7le3n2ya72s",
        "status": "active",
        "uptime": "100",
        "commision": "5",
        "apr": null,
        "price": "",
        "staked_user": "",
        "staked_amount": ""
    },
    {
        "name": "Loyal",
        "description": "",
        "logo": "loyal.svg",
        "url": "https://www.joinloyal.io/",
        "address": "https://testnet.explorer.tcnetwork.io/loyal/validator/loyalvaloper16re2zprhnekq62qmcuh7v0dxtsa7le3nphpqn2",
        "status": "active",
        "uptime": "100",
        "commision": "5",
        "apr": null,
        "price": "",
        "staked_user": "",
        "staked_amount": ""
    }
]